bnn_for_14C_calibration/__init__.py
bnn_for_14C_calibration/bnn_models_built_in.py
bnn_for_14C_calibration/bnn_models_built_in_utils.py
bnn_for_14C_calibration/calib_plot_functions.py
bnn_for_14C_calibration/calibration.py
bnn_for_14C_calibration/calibration_utils.py
bnn_for_14C_calibration/manage_cache.py
bnn_for_14C_calibration/utils.py
bnn_for_14C_calibration/data/IntCal20/IntCal20_completed.csv
bnn_for_14C_calibration/data/exogenous_variables/be10.csv
bnn_for_14C_calibration/data/exogenous_variables/glopis.csv
bnn_for_14c_calibration-0.1.0.dist-info/licenses/COPYING
bnn_for_14c_calibration-0.1.0.dist-info/METADATA
bnn_for_14c_calibration-0.1.0.dist-info/WHEEL
bnn_for_14c_calibration-0.1.0.dist-info/top_level.txt
bnn_for_14c_calibration-0.1.0.dist-info/RECORD
