Metadata-Version: 2.4
Name: bnn_for_14C_calibration
Version: 0.1.0
Summary: Bayesian Neural Networks methods for radiocarbon (14C) calibration
Author-email: Destin ASHUZA CIRUMANGA <destin.cirumanga@gmail.com>
License:                     GNU GENERAL PUBLIC LICENSE
Project-URL: Homepage, https://github.com/dest-ash/bnn_for_14C_calibration
Project-URL: Repository, https://github.com/dest-ash/bnn_for_14C_calibration.git
Keywords: Bayesian Neural Network,radiocarbon calibration,14C
Classifier: Programming Language :: Python :: 3
Classifier: Operating System :: OS Independent
Requires-Python: ==3.9.13
License-File: COPYING
Requires-Dist: numpy==1.23.2
Requires-Dist: matplotlib==3.5.3
Requires-Dist: pandas==1.4.4
Requires-Dist: gdown==5.2.0
Requires-Dist: scikit-learn==1.1.2
Requires-Dist: tensorflow==2.9.1
Requires-Dist: tensorflow-probability==0.17.0
Provides-Extra: notebook
Requires-Dist: jupyter; extra == "notebook"
Dynamic: license-file
